floe/__init__.py
floe/connector.py
floe/exceptions.py
floe/fileapi.py
floe/helpers.py
floe/mysqlapi.py
floe/otel_instrumentation.py
floe/restapi.py
floe/restserver.py
floe/version.py
floe-0.1.0.dist-info/licenses/LICENSE
floe-0.1.0.dist-info/METADATA
floe-0.1.0.dist-info/WHEEL
floe-0.1.0.dist-info/top_level.txt
floe-0.1.0.dist-info/RECORD
